{"@type":"order","orders":[{"billing_detail":{"address":{"country":"GB","address_line_1":"Schifferstrasse 15","address_line_2":null,"post_code":"SL13GG","town_city":"Slough","county":"England"},"name":{"first_name":"Marco","title":"Mr","last_name":"Schmidt"},"contact_detail":{"email":"marco.schmidt@deininger.co.uk","telephone":{"type":"phone","number":"0044 (0)1753877246"}}},"o_id":"449000","tender_lines":[{"value":{"currency":"GBP","amount":"100.00"},"type":"Card","card_detail":{"type":"visa","number":"4xxxxxxxxxxx8602","expiry_date":"01/13","transaction_reference":"3800101013550143","auth_code":"895412","threed_secure":"","fraud_score":"SECURITY CODE MATCH ONLY"},"tl_id":"1"},{"value":{"currency":"GBP","amount":"100.50"},"type":"Store Credit","card_detail":null,"tl_id":"2"}],"channel":"JC-INTL","cust_id":"449060","shipping_method":"uklondonstandard","order_date":"2011-05-30 12:33:15","delivery_detail":{"address":{"country":"GB","address_line_1":"Windsor Road","address_line_2":"Mosaic Apartments","post_code":"SL13GG","town_city":"Slough","county":"England"},"name":{"first_name":"Marco","title":"Mr","last_name":"Schmidt"},"order_line":[{"description":"Glenys","ol_id":"31328","ol_seq":"1","quantity":"1","sku":"172894-089","unit_net_price":{"value":{"currency":"GBP","amount":"150.50"}},"tax":{"value":{"currency":"GBP","amount":"25.00"}},"duties":{"value":{"currency":"GBP","amount":"0"}}}],"gift_message":"Happy Birthday dude."},"gross_total":{"value":{"currency":"GBP","amount":"200.50"}},"postage":{"value":{"currency":"GBP","amount":"25.00"}},"promotion_basket":{"value":{"currency":"GBP","amount":"0.00"},"type":"free_shipping","description":"XMAS Free Shipping","pb_id":"44087"},"promotion_line":{"value":{"currency":"GBP","amount":"20.00"},"type":"percentage_discount","description":"Extra 10% Off","pl_id":"4487","order_line_id":"31328"},"comments":["This is a comment"],"preauth_response_reference":20000081}],"merchant_url":"www.jimmychoo.com"}

